setup.py
sunnydayss/__init__.py
sunnydayss/sunnydayss.py
sunnydayss.egg-info/PKG-INFO
sunnydayss.egg-info/SOURCES.txt
sunnydayss.egg-info/dependency_links.txt
sunnydayss.egg-info/requires.txt
sunnydayss.egg-info/top_level.txt