Metadata-Version: 2.1
Name: sunnydayss
Version: 1.0.0
Summary: Weather forecast data
Author: bluemario8
License: MIT
